[{"Date":"04/12/2022","Transaction":1,"Value":194870,"Symbol":"CDZI"},{"Date":"04/11/2022","Transaction":1,"Value":199570,"Symbol":"CDZI"},{"Date":"04/04/2022","Transaction":1,"Value":11955,"Symbol":"CDZI"},{"Date":"04/04/2022","Transaction":1,"Value":21408,"Symbol":"CDZI"},{"Date":"04/01/2022","Transaction":1,"Value":1278,"Symbol":"CDZI"},{"Date":"04/01/2022","Transaction":1,"Value":58491,"Symbol":"CDZI"},{"Date":"04/01/2022","Transaction":1,"Value":94149,"Symbol":"CDZI"},{"Date":"03/20/2022","Transaction":1,"Value":4999998,"Symbol":"CDZI"},{"Date":"03/18/2022","Transaction":-1,"Value":103327,"Symbol":"MSEX"},{"Date":"03/17/2022","Transaction":1,"Value":89358,"Symbol":"ARIS"},{"Date":"03/04/2022","Transaction":-1,"Value":316856,"Symbol":"MSEX"},{"Date":"03/04/2022","Transaction":-1,"Value":105000,"Symbol":"MSEX"},{"Date":"03/03/2022","Transaction":-1,"Value":50427,"Symbol":"MSEX"},{"Date":"02/25/2022","Transaction":-1,"Value":58962,"Symbol":"AWR"},{"Date":"01/18/2022","Transaction":0,"Value":217949,"Symbol":"ZWS"},{"Date":"12/16/2021","Transaction":-1,"Value":85476,"Symbol":"CWT"},{"Date":"12/16/2021","Transaction":1,"Value":106218,"Symbol":"CDZI"},{"Date":"12/15/2021","Transaction":-1,"Value":30422,"Symbol":"CWT"},{"Date":"12/15/2021","Transaction":1,"Value":113400,"Symbol":"CDZI"},{"Date":"12/13/2021","Transaction":0,"Value":7205,"Symbol":"ZWS"},{"Date":"12/13/2021","Transaction":-1,"Value":18806,"Symbol":"ZWS"},{"Date":"12/13/2021","Transaction":1,"Value":90000,"Symbol":"CDZI"},{"Date":"12/08/2021","Transaction":-1,"Value":99654,"Symbol":"WTRG"},{"Date":"12/07/2021","Transaction":-1,"Value":160243,"Symbol":"SJW"},{"Date":"12/03/2021","Transaction":-1,"Value":136820,"Symbol":"SJW"},{"Date":"12/03/2021","Transaction":-1,"Value":47820,"Symbol":"AWR"},{"Date":"12/01/2021","Transaction":-1,"Value":32935,"Symbol":"AWR"},{"Date":"11/22/2021","Transaction":0,"Value":193023,"Symbol":"AWK"},{"Date":"11/22/2021","Transaction":-1,"Value":406335,"Symbol":"AWK"},{"Date":"11/22/2021","Transaction":-1,"Value":608916,"Symbol":"AWK"},{"Date":"11/19/2021","Transaction":0,"Value":218174,"Symbol":"AWK"},{"Date":"11/19/2021","Transaction":0,"Value":1603798,"Symbol":"AWK"},{"Date":"11/19/2021","Transaction":0,"Value":181998,"Symbol":"AWK"},{"Date":"11/19/2021","Transaction":-1,"Value":504104,"Symbol":"AWK"},{"Date":"11/19/2021","Transaction":-1,"Value":4269080,"Symbol":"AWK"},{"Date":"11/19/2021","Transaction":-1,"Value":718506,"Symbol":"AWK"},{"Date":"11/16/2021","Transaction":-1,"Value":52652,"Symbol":"MSEX"},{"Date":"11/12/2021","Transaction":-1,"Value":686424,"Symbol":"AWR"},{"Date":"11/12/2021","Transaction":0,"Value":21528457,"Symbol":"ZWS"},{"Date":"11/12/2021","Transaction":-1,"Value":1124173,"Symbol":"ZWS"},{"Date":"11/11/2021","Transaction":-1,"Value":1280812,"Symbol":"ZWS"},{"Date":"11/11/2021","Transaction":-1,"Value":934642,"Symbol":"ZWS"},{"Date":"11/05/2021","Transaction":0,"Value":216053,"Symbol":"ZWS"},{"Date":"11/03/2021","Transaction":-1,"Value":301364,"Symbol":"MSEX"},{"Date":"10/29/2021","Transaction":-1,"Value":1106577,"Symbol":"ZWS"},{"Date":"10/29/2021","Transaction":-1,"Value":4458200,"Symbol":"ZWS"},{"Date":"10/29/2021","Transaction":-1,"Value":1490055,"Symbol":"ZWS"},{"Date":"10/29/2021","Transaction":-1,"Value":694232,"Symbol":"ZWS"},{"Date":"10/29/2021","Transaction":-1,"Value":2544125,"Symbol":"ZWS"},{"Date":"10/29/2021","Transaction":-1,"Value":544603,"Symbol":"ZWS"},{"Date":"10/29/2021","Transaction":-1,"Value":1113460,"Symbol":"ZWS"},{"Date":"10/29/2021","Transaction":-1,"Value":1596114,"Symbol":"ZWS"},{"Date":"10/29/2021","Transaction":-1,"Value":23225641,"Symbol":"ZWS"},{"Date":"10/26/2021","Transaction":1,"Value":19500,"Symbol":"ARIS"},{"Date":"10/26/2021","Transaction":1,"Value":199992,"Symbol":"ARIS"},{"Date":"10/26/2021","Transaction":1,"Value":99996,"Symbol":"ARIS"},{"Date":"10/26/2021","Transaction":1,"Value":999999,"Symbol":"ARIS"},{"Date":"09/27/2021","Transaction":-1,"Value":114115,"Symbol":"MSEX"},{"Date":"09/07/2021","Transaction":-1,"Value":48500,"Symbol":"AWR"},{"Date":"09/03/2021","Transaction":-1,"Value":337683,"Symbol":"MSEX"},{"Date":"09/02/2021","Transaction":-1,"Value":16280,"Symbol":"CWT"},{"Date":"08/31/2021","Transaction":-1,"Value":45955,"Symbol":"AWR"},{"Date":"08/30/2021","Transaction":-1,"Value":100000,"Symbol":"WTRG"},{"Date":"08/23/2021","Transaction":-1,"Value":227417,"Symbol":"AWR"},{"Date":"08/16/2021","Transaction":-1,"Value":199961,"Symbol":"AWR"},{"Date":"08/13/2021","Transaction":-1,"Value":53232,"Symbol":"AWR"},{"Date":"08/13/2021","Transaction":-1,"Value":311174,"Symbol":"AWR"},{"Date":"08/12/2021","Transaction":-1,"Value":44450,"Symbol":"CWT"},{"Date":"08/10/2021","Transaction":-1,"Value":316668,"Symbol":"MSEX"},{"Date":"08/09/2021","Transaction":-1,"Value":107308,"Symbol":"MSEX"},{"Date":"08/06/2021","Transaction":-1,"Value":33052,"Symbol":"MSEX"},{"Date":"08/05/2021","Transaction":-1,"Value":320316,"Symbol":"MSEX"},{"Date":"08/05/2021","Transaction":-1,"Value":2209150,"Symbol":"WTRG"},{"Date":"08/04/2021","Transaction":-1,"Value":31885,"Symbol":"CWT"},{"Date":"08/04/2021","Transaction":-1,"Value":47744,"Symbol":"CWT"},{"Date":"08/04/2021","Transaction":-1,"Value":580334,"Symbol":"AWR"},{"Date":"06/21/2021","Transaction":-1,"Value":103400,"Symbol":"WTRG"},{"Date":"06/16/2021","Transaction":-1,"Value":86500,"Symbol":"MSEX"},{"Date":"06/15/2021","Transaction":-1,"Value":90862,"Symbol":"CWT"},{"Date":"06/07/2021","Transaction":-1,"Value":28500,"Symbol":"CWT"},{"Date":"06/04/2021","Transaction":-1,"Value":25851,"Symbol":"MSEX"},{"Date":"06/03/2021","Transaction":-1,"Value":212987,"Symbol":"MSEX"},{"Date":"06/01/2021","Transaction":-1,"Value":338788,"Symbol":"MSEX"},{"Date":"05/27/2021","Transaction":-1,"Value":16752,"Symbol":"WTRG"},{"Date":"05/20/2021","Transaction":-1,"Value":102158,"Symbol":"AWK"},{"Date":"05/18/2021","Transaction":-1,"Value":52446,"Symbol":"MSEX"},{"Date":"05/06/2021","Transaction":-1,"Value":23598,"Symbol":"CWT"},{"Date":"05/05/2021","Transaction":-1,"Value":50155,"Symbol":"CWT"}]